codeplug.py
codeplug-0.2.0.dist-info/DESCRIPTION.rst
codeplug-0.2.0.dist-info/METADATA
codeplug-0.2.0.dist-info/RECORD
codeplug-0.2.0.dist-info/WHEEL
codeplug-0.2.0.dist-info/entry_points.txt
codeplug-0.2.0.dist-info/metadata.json
codeplug-0.2.0.dist-info/top_level.txt
