Metadata-Version: 2.0
Name: codeplug
Version: 0.2.0
Summary: codeplug decoder and builder for Motorola radios
Home-page: https://github.com/george-hopkins/codeplug
Author: George Hopkins
Author-email: george-hopkins@null.net
License: MIT
Keywords: motorola mototrbo cps ctb codeplug dmr
Platform: UNKNOWN
Classifier: Development Status :: 4 - Beta
Classifier: Intended Audience :: Developers
Classifier: Intended Audience :: Telecommunications Industry
Classifier: Topic :: Communications :: Ham Radio
Classifier: License :: OSI Approved :: MIT License
Classifier: Programming Language :: Python :: 3
Classifier: Programming Language :: Python :: 3.4
Classifier: Programming Language :: Python :: 3.5
Classifier: Programming Language :: Python :: 3.6
Requires-Dist: cryptography (>=1.6)
Requires-Dist: lxml (>=3)
Requires-Dist: pyOpenSSL (>=17)
Provides-Extra: dev
Provides-Extra: test
